{
  "generator-jhipster": {
    "promptValues": {
      "packageName": "com.reservation.sport",
      "nativeLanguage": "pl"
    },
    "jhipsterVersion": "4.14.4",
    "baseName": "ReservationApp",
    "packageName": "com.reservation.sport",
    "packageFolder": "com/reservation/sport",
    "serverPort": "8080",
    "authenticationType": "jwt",
    "cacheProvider": "ehcache",
    "enableHibernateCache": false,
    "websocket": false,
    "databaseType": "sql",
    "devDatabaseType": "postgresql",
    "prodDatabaseType": "postgresql",
    "searchEngine": false,
    "messageBroker": false,
    "serviceDiscoveryType": false,
    "buildTool": "maven",
    "enableSocialSignIn": false,
    "enableSwaggerCodegen": false,
    "jwtSecretKey": "47ff0f8fa6d1485f7eae8ca8c6a0108c48a5e1bd",
    "clientFramework": "angularX",
    "useSass": true,
    "clientPackageManager": "yarn",
    "applicationType": "monolith",
    "testFrameworks": [],
    "jhiPrefix": "jhi",
    "enableTranslation": true,
    "nativeLanguage": "pl",
    "languages": [
      "pl"
    ]
  }
}